MANIFEST.in
README.rst
setup.py
kairios/__init__.py
kairios.egg-info/PKG-INFO
kairios.egg-info/SOURCES.txt
kairios.egg-info/dependency_links.txt
kairios.egg-info/not-zip-safe
kairios.egg-info/top_level.txt
kairios/templatetags/__init__.py
kairios/templatetags/kairios_tags.py