Metadata-Version: 1.1
Name: kairios
Version: 0.3
Summary: utilities for publishing events as a calendar
Home-page: http://github.com/eldarion/kairios
Author: Eldarion
Author-email: development@eldarion.com
License: BSD
Platform: UNKNOWN
Classifier: Development Status :: 3 - Alpha
Classifier: Environment :: Web Environment
Classifier: Intended Audience :: Developers
Classifier: License :: OSI Approved :: BSD License
Classifier: Operating System :: OS Independent
Classifier: Programming Language :: Python
Classifier: Framework :: Django
